Metadata-Version: 1.1
Name: django-versionfield2
Version: 0.5.0
Summary: A DB Independent Custom Django Field for storing Version numbers for fast indexing
Home-page: https://github.com/tonioo/django-versionfield
Author: Antoine Nguyen
Author-email: tonio@ngyn.org
License: BSD
Platform: UNKNOWN
Classifier: Development Status :: 3 - Alpha
Classifier: Framework :: Django
Classifier: Intended Audience :: Developers
Classifier: License :: OSI Approved :: BSD License
Classifier: Operating System :: OS Independent
Classifier: Programming Language :: Python
Classifier: Topic :: Internet :: WWW/HTTP
